odoo8_addon_connector_prestashop-8.0.1.0.5.99.dev5-py2.7-nspkg.pth
odoo8_addon_connector_prestashop-8.0.1.0.5.99.dev5.dist-info/METADATA
odoo8_addon_connector_prestashop-8.0.1.0.5.99.dev5.dist-info/RECORD
odoo8_addon_connector_prestashop-8.0.1.0.5.99.dev5.dist-info/WHEEL
odoo8_addon_connector_prestashop-8.0.1.0.5.99.dev5.dist-info/namespace_packages.txt
odoo8_addon_connector_prestashop-8.0.1.0.5.99.dev5.dist-info/top_level.txt
odoo_addons/connector_prestashop/README.rst
odoo_addons/connector_prestashop/__init__.py
odoo_addons/connector_prestashop/__openerp__.py
odoo_addons/connector_prestashop/backend.py
odoo_addons/connector_prestashop/connector.py
odoo_addons/connector_prestashop/consumer.py
odoo_addons/connector_prestashop/data/cron.xml
odoo_addons/connector_prestashop/data/ecommerce_data.xml
odoo_addons/connector_prestashop/data/product_decimal_precision.xml
odoo_addons/connector_prestashop/i18n/connector_prestashop.pot
odoo_addons/connector_prestashop/i18n/es.po
odoo_addons/connector_prestashop/i18n/fr.po
odoo_addons/connector_prestashop/models/__init__.py
odoo_addons/connector_prestashop/models/connector.py
odoo_addons/connector_prestashop/models/account_invoice/__init__.py
odoo_addons/connector_prestashop/models/account_invoice/common.py
odoo_addons/connector_prestashop/models/account_invoice/importer.py
odoo_addons/connector_prestashop/models/account_tax/__init__.py
odoo_addons/connector_prestashop/models/account_tax/common.py
odoo_addons/connector_prestashop/models/account_tax/importer.py
odoo_addons/connector_prestashop/models/account_tax_group/__init__.py
odoo_addons/connector_prestashop/models/account_tax_group/common.py
odoo_addons/connector_prestashop/models/account_tax_group/importer.py
odoo_addons/connector_prestashop/models/binding/__init__.py
odoo_addons/connector_prestashop/models/binding/common.py
odoo_addons/connector_prestashop/models/delivery_carrier/__init__.py
odoo_addons/connector_prestashop/models/delivery_carrier/common.py
odoo_addons/connector_prestashop/models/delivery_carrier/importer.py
odoo_addons/connector_prestashop/models/mail_message/__init__.py
odoo_addons/connector_prestashop/models/mail_message/common.py
odoo_addons/connector_prestashop/models/mail_message/importer.py
odoo_addons/connector_prestashop/models/payment/__init__.py
