Metadata-Version: 2.1
Name: odoo8-addon-connector-prestashop
Version: 8.0.1.0.5.99.dev5
Summary: PrestaShop-Odoo connector
Home-page: https://github.com/OCA/connector-prestashop
Author: Akretion,Camptocamp,AvanzOSC,Tecnativa,Odoo Community Association (OCA)
Author-email: support@odoo-community.org
License: AGPL-3
Platform: UNKNOWN
Classifier: Programming Language :: Python
Classifier: Framework :: Odoo
Classifier: License :: OSI Approved :: GNU Affero General Public License v3
Requires-Python: ~=2.7
Requires-Dist: html2text
Requires-Dist: odoo8-addon-connector-ecommerce
Requires-Dist: odoo8-addon-product-m2mcategories
Requires-Dist: odoo8-addon-product-multi-image
Requires-Dist: odoo8-addon-product-variant-cost-price
Requires-Dist: odoo8-addon-product-variant-supplierinfo
Requires-Dist: odoo (<9.0a,>=8.0a)
Requires-Dist: prestapyt
